odoo/addons/fastapi_auth_jwt_demo/README.rst
odoo/addons/fastapi_auth_jwt_demo/__init__.py
odoo/addons/fastapi_auth_jwt_demo/__manifest__.py
odoo/addons/fastapi_auth_jwt_demo/demo/fastapi_endpoint.xml
odoo/addons/fastapi_auth_jwt_demo/i18n/fastapi_auth_jwt_demo.pot
odoo/addons/fastapi_auth_jwt_demo/i18n/it.po
odoo/addons/fastapi_auth_jwt_demo/models/__init__.py
odoo/addons/fastapi_auth_jwt_demo/models/fastapi_endpoint.py
odoo/addons/fastapi_auth_jwt_demo/readme/DESCRIPTION.rst
odoo/addons/fastapi_auth_jwt_demo/routers/__init__.py
odoo/addons/fastapi_auth_jwt_demo/routers/auth_jwt_demo_api.py
odoo/addons/fastapi_auth_jwt_demo/static/description/icon.png
odoo/addons/fastapi_auth_jwt_demo/static/description/index.html
odoo/addons/fastapi_auth_jwt_demo/tests/__init__.py
odoo/addons/fastapi_auth_jwt_demo/tests/test_fastapi_auth_jwt_demo.py
odoo_addon_fastapi_auth_jwt_demo-16.0.2.0.1.3.dist-info/METADATA
odoo_addon_fastapi_auth_jwt_demo-16.0.2.0.1.3.dist-info/WHEEL
odoo_addon_fastapi_auth_jwt_demo-16.0.2.0.1.3.dist-info/top_level.txt
odoo_addon_fastapi_auth_jwt_demo-16.0.2.0.1.3.dist-info/RECORD
