Metadata-Version: 2.1
Name: odoo-addon-fastapi_auth_jwt_demo
Version: 16.0.2.0.1.3
Summary: Test/demo module for fastapi_auth_jwt.
Home-page: https://github.com/OCA/rest-framework
Author: ACSONE SA/NV,Odoo Community Association (OCA)
Author-email: support@odoo-community.org
License: LGPL-3
Classifier: Programming Language :: Python
Classifier: Framework :: Odoo
Classifier: Framework :: Odoo :: 16.0
Classifier: License :: OSI Approved :: GNU Lesser General Public License v3 (LGPLv3)
Requires-Python: >=3.10
Requires-Dist: odoo-addon-auth-jwt-demo<16.1dev,>=16.0dev
Requires-Dist: odoo-addon-fastapi-auth-jwt<16.1dev,>=16.0dev
Requires-Dist: odoo<16.1dev,>=16.0a
